wordwise/__init__.py
wordwise/__version__.py
wordwise/core.py
wordwise/utils.py
wordwise-0.0.5.dist-info/LICENSE
wordwise-0.0.5.dist-info/METADATA
wordwise-0.0.5.dist-info/WHEEL
wordwise-0.0.5.dist-info/top_level.txt
wordwise-0.0.5.dist-info/RECORD
