Metadata-Version: 2.1
Name: wordwise
Version: 0.0.5
Summary: Keyword extraction using transformer-based language models
Home-page: https://github.com/jaketae/wordwise
Author: Jake Tae
Author-email: jaesungtae@gmail.com
License: UNKNOWN
Platform: UNKNOWN
Classifier: Programming Language :: Python :: 3
Classifier: Programming Language :: Python :: 3.6
Classifier: Programming Language :: Python :: 3.7
Classifier: Programming Language :: Python :: 3.8
Classifier: Programming Language :: Python :: 3.9
Classifier: Programming Language :: Python :: 3.10
Classifier: License :: OSI Approved :: MIT License
Classifier: Operating System :: OS Independent
Classifier: Intended Audience :: Developers
Classifier: Intended Audience :: Science/Research
Classifier: Topic :: Scientific/Engineering :: Artificial Intelligence
Requires-Python: >=3.6
Requires-Dist: transformers (>=3.5.1)
Requires-Dist: torch (>=1.6.0)
Requires-Dist: scikit-learn (>=0.23.2)
Requires-Dist: spacy (>=2.3.2)
Requires-Dist: spacy-transformers (>=1.1)
